{
    "last_updated": "Sep. 29 at 5:56 p.m. Pacific Time",
    "last_updated_iso": "2025-09-29T17:56:14.267362-07:00",
    "teams": [
        {
            "team_id": 141,
            "team_name": "Toronto Blue Jays",
            "wins": 94,
            "losses": 68,
            "winning_percentage": ".580",
            "division_rank": "1",
            "league_rank": "2",
            "sport_rank": "4",
            "games_back": "-",
            "division_games_back": "-",
            "league_games_back": "-",
            "streak_type": "wins",
            "streak_number": 4,
            "magic_number": "-",
            "elimination_number": "-",
            "division_name": "American League East",
            "league_name": "American League",
            "games_played": 162,
            "runs_scored": 798,
            "runs_against": 721,
            "run_differential": 77
        },
        {
            "team_id": 147,
            "team_name": "New York Yankees",
            "wins": 94,
            "losses": 68,
            "winning_percentage": ".580",
            "division_rank": "2",
            "league_rank": "1",
            "sport_rank": "3",
            "games_back": "-",
            "division_games_back": "-",
            "league_games_back": "-",
            "streak_type": "wins",
            "streak_number": 8,
            "magic_number": null,
            "elimination_number": "1",
            "division_name": "American League East",
            "league_name": "American League",
            "games_played": 162,
            "runs_scored": 849,
            "runs_against": 685,
            "run_differential": 164
        },
        {
            "team_id": 111,
            "team_name": "Boston Red Sox",
            "wins": 89,
            "losses": 73,
            "winning_percentage": ".549",
            "division_rank": "3",
            "league_rank": "4",
            "sport_rank": "9",
            "games_back": 5,
            "division_games_back": 5,
            "league_games_back": 5,
            "streak_type": "wins",
            "streak_number": 1,
            "magic_number": null,
            "elimination_number": "E",
            "division_name": "American League East",
            "league_name": "American League",
            "games_played": 162,
            "runs_scored": 786,
            "runs_against": 676,
            "run_differential": 110
        },
        {
            "team_id": 139,
            "team_name": "Tampa Bay Rays",
            "wins": 77,
            "losses": 85,
            "winning_percentage": ".475",
            "division_rank": "4",
            "league_rank": "10",
            "sport_rank": "21",
            "games_back": 17,
            "division_games_back": 17,
            "league_games_back": 17,
            "streak_type": "losses",
            "streak_number": 4,
            "magic_number": null,
            "elimination_number": "E",
            "division_name": "American League East",
            "league_name": "American League",
            "games_played": 162,
            "runs_scored": 714,
            "runs_against": 683,
            "run_differential": 31
        },
        {
            "team_id": 110,
            "team_name": "Baltimore Orioles",
            "wins": 75,
            "losses": 87,
            "winning_percentage": ".463",
            "division_rank": "5",
            "league_rank": "12",
            "sport_rank": "24",
            "games_back": 19,
            "division_games_back": 19,
            "league_games_back": 19,
            "streak_type": "losses",
            "streak_number": 3,
            "magic_number": null,
            "elimination_number": "E",
            "division_name": "American League East",
            "league_name": "American League",
            "games_played": 162,
            "runs_scored": 677,
            "runs_against": 788,
            "run_differential": -111
        },
        {
            "team_id": 114,
            "team_name": "Cleveland Guardians",
            "wins": 88,
            "losses": 74,
            "winning_percentage": ".543",
            "division_rank": "1",
            "league_rank": "5",
            "sport_rank": "10",
            "games_back": "-",
            "division_games_back": "-",
            "league_games_back": 6,
            "streak_type": "wins",
            "streak_number": 2,
            "magic_number": "-",
            "elimination_number": "-",
            "division_name": "American League Central",
            "league_name": "American League",
            "games_played": 162,
            "runs_scored": 643,
            "runs_against": 649,
            "run_differential": -6
        },
        {
            "team_id": 116,
            "team_name": "Detroit Tigers",
            "wins": 87,
            "losses": 75,
            "winning_percentage": ".537",
            "division_rank": "2",
            "league_rank": "6",
            "sport_rank": "11",
            "games_back": 1,
            "division_games_back": 1,
            "league_games_back": 7,
            "streak_type": "losses",
            "streak_number": 1,
            "magic_number": null,
            "elimination_number": "E",
            "division_name": "American League Central",
            "league_name": "American League",
            "games_played": 162,
            "runs_scored": 758,
            "runs_against": 691,
            "run_differential": 67
        },
        {
            "team_id": 118,
            "team_name": "Kansas City Royals",
            "wins": 82,
            "losses": 80,
            "winning_percentage": ".506",
            "division_rank": "3",
            "league_rank": "8",
            "sport_rank": "15",
            "games_back": 6,
            "division_games_back": 6,
            "league_games_back": 12,
            "streak_type": "wins",
            "streak_number": 2,
            "magic_number": null,
            "elimination_number": "E",
            "division_name": "American League Central",
            "league_name": "American League",
            "games_played": 162,
            "runs_scored": 651,
            "runs_against": 637,
            "run_differential": 14
        },
        {
            "team_id": 142,
            "team_name": "Minnesota Twins",
            "wins": 70,
            "losses": 92,
            "winning_percentage": ".432",
            "division_rank": "4",
            "league_rank": "14",
            "sport_rank": "27",
            "games_back": 18,
            "division_games_back": 18,
            "league_games_back": 24,
            "streak_type": "losses",
            "streak_number": 1,
            "magic_number": null,
            "elimination_number": "E",
            "division_name": "American League Central",
            "league_name": "American League",
            "games_played": 162,
            "runs_scored": 678,
            "runs_against": 773,
            "run_differential": -95
        },
        {
            "team_id": 145,
            "team_name": "Chicago White Sox",
            "wins": 60,
            "losses": 102,
            "winning_percentage": ".370",
            "division_rank": "5",
            "league_rank": "15",
            "sport_rank": "29",
            "games_back": 28,
            "division_games_back": 28,
            "league_games_back": 34,
            "streak_type": "wins",
            "streak_number": 1,
            "magic_number": null,
            "elimination_number": "E",
            "division_name": "American League Central",
            "league_name": "American League",
            "games_played": 162,
            "runs_scored": 647,
            "runs_against": 742,
            "run_differential": -95
        },
        {
            "team_id": 136,
            "team_name": "Seattle Mariners",
            "wins": 90,
            "losses": 72,
            "winning_percentage": ".556",
            "division_rank": "1",
            "league_rank": "3",
            "sport_rank": "8",
            "games_back": "-",
            "division_games_back": "-",
            "league_games_back": 4,
            "streak_type": "losses",
            "streak_number": 3,
            "magic_number": "-",
            "elimination_number": "-",
            "division_name": "American League West",
            "league_name": "American League",
            "games_played": 162,
            "runs_scored": 766,
            "runs_against": 694,
            "run_differential": 72
        },
        {
            "team_id": 117,
            "team_name": "Houston Astros",
            "wins": 87,
            "losses": 75,
            "winning_percentage": ".537",
            "division_rank": "2",
            "league_rank": "7",
            "sport_rank": "12",
            "games_back": 3,
            "division_games_back": 3,
            "league_games_back": 7,
            "streak_type": "wins",
            "streak_number": 2,
            "magic_number": null,
            "elimination_number": "E",
            "division_name": "American League West",
            "league_name": "American League",
            "games_played": 162,
            "runs_scored": 686,
            "runs_against": 665,
            "run_differential": 21
        },
        {
            "team_id": 140,
            "team_name": "Texas Rangers",
            "wins": 81,
            "losses": 81,
            "winning_percentage": ".500",
            "division_rank": "3",
            "league_rank": "9",
            "sport_rank": "17",
            "games_back": 9,
            "division_games_back": 9,
            "league_games_back": 13,
            "streak_type": "losses",
            "streak_number": 2,
            "magic_number": null,
            "elimination_number": "E",
            "division_name": "American League West",
            "league_name": "American League",
            "games_played": 162,
            "runs_scored": 684,
            "runs_against": 605,
            "run_differential": 79
        },
        {
            "team_id": 133,
            "team_name": "Athletics",
            "wins": 76,
            "losses": 86,
            "winning_percentage": ".469",
            "division_rank": "4",
            "league_rank": "11",
            "sport_rank": "22",
            "games_back": 14,
            "division_games_back": 14,
            "league_games_back": 18,
            "streak_type": "losses",
            "streak_number": 2,
            "magic_number": null,
            "elimination_number": "E",
            "division_name": "American League West",
            "league_name": "American League",
            "games_played": 162,
            "runs_scored": 733,
            "runs_against": 817,
            "run_differential": -84
        },
        {
            "team_id": 108,
            "team_name": "Los Angeles Angels",
            "wins": 72,
            "losses": 90,
            "winning_percentage": ".444",
            "division_rank": "5",
            "league_rank": "13",
            "sport_rank": "25",
            "games_back": 18,
            "division_games_back": 18,
            "league_games_back": 22,
            "streak_type": "losses",
            "streak_number": 2,
            "magic_number": null,
            "elimination_number": "E",
            "division_name": "American League West",
            "league_name": "American League",
            "games_played": 162,
            "runs_scored": 673,
            "runs_against": 837,
            "run_differential": -164
        },
        {
            "team_id": 143,
            "team_name": "Philadelphia Phillies",
            "wins": 96,
            "losses": 66,
            "winning_percentage": ".593",
            "division_rank": "1",
            "league_rank": "2",
            "sport_rank": "2",
            "games_back": "-",
            "division_games_back": "-",
            "league_games_back": 1,
            "streak_type": "wins",
            "streak_number": 1,
            "magic_number": "-",
            "elimination_number": "-",
            "division_name": "National League East",
            "league_name": "National League",
            "games_played": 162,
            "runs_scored": 778,
            "runs_against": 648,
            "run_differential": 130
        },
        {
            "team_id": 121,
            "team_name": "New York Mets",
            "wins": 83,
            "losses": 79,
            "winning_percentage": ".512",
            "division_rank": "2",
            "league_rank": "7",
            "sport_rank": "14",
            "games_back": 13,
            "division_games_back": 13,
            "league_games_back": 14,
            "streak_type": "losses",
            "streak_number": 1,
            "magic_number": null,
            "elimination_number": "E",
            "division_name": "National League East",
            "league_name": "National League",
            "games_played": 162,
            "runs_scored": 766,
            "runs_against": 715,
            "run_differential": 51
        },
        {
            "team_id": 146,
            "team_name": "Miami Marlins",
            "wins": 79,
            "losses": 83,
            "winning_percentage": ".488",
            "division_rank": "3",
            "league_rank": "10",
            "sport_rank": "19",
            "games_back": 17,
            "division_games_back": 17,
            "league_games_back": 18,
            "streak_type": "wins",
            "streak_number": 1,
            "magic_number": null,
            "elimination_number": "E",
            "division_name": "National League East",
            "league_name": "National League",
            "games_played": 162,
            "runs_scored": 709,
            "runs_against": 798,
            "run_differential": -89
        },
        {
            "team_id": 144,
            "team_name": "Atlanta Braves",
            "wins": 76,
            "losses": 86,
            "winning_percentage": ".469",
            "division_rank": "4",
            "league_rank": "12",
            "sport_rank": "23",
            "games_back": 20,
            "division_games_back": 20,
            "league_games_back": 21,
            "streak_type": "wins",
            "streak_number": 1,
            "magic_number": null,
            "elimination_number": "E",
            "division_name": "National League East",
            "league_name": "National League",
            "games_played": 162,
            "runs_scored": 724,
            "runs_against": 734,
            "run_differential": -10
        },
        {
            "team_id": 120,
            "team_name": "Washington Nationals",
            "wins": 66,
            "losses": 96,
            "winning_percentage": ".407",
            "division_rank": "5",
            "league_rank": "14",
            "sport_rank": "28",
            "games_back": 30,
            "division_games_back": 30,
            "league_games_back": 31,
            "streak_type": "losses",
            "streak_number": 1,
            "magic_number": null,
            "elimination_number": "E",
            "division_name": "National League East",
            "league_name": "National League",
            "games_played": 162,
            "runs_scored": 687,
            "runs_against": 899,
            "run_differential": -212
        },
        {
            "team_id": 158,
            "team_name": "Milwaukee Brewers",
            "wins": 97,
            "losses": 65,
            "winning_percentage": ".599",
            "division_rank": "1",
            "league_rank": "1",
            "sport_rank": "1",
            "games_back": "-",
            "division_games_back": "-",
            "league_games_back": "-",
            "streak_type": "wins",
            "streak_number": 1,
            "magic_number": "-",
            "elimination_number": "-",
            "division_name": "National League Central",
            "league_name": "National League",
            "games_played": 162,
            "runs_scored": 806,
            "runs_against": 634,
            "run_differential": 172
        },
        {
            "team_id": 112,
            "team_name": "Chicago Cubs",
            "wins": 92,
            "losses": 70,
            "winning_percentage": ".568",
            "division_rank": "2",
            "league_rank": "4",
            "sport_rank": "6",
            "games_back": 5,
            "division_games_back": 5,
            "league_games_back": 5,
            "streak_type": "wins",
            "streak_number": 3,
            "magic_number": null,
            "elimination_number": "E",
            "division_name": "National League Central",
            "league_name": "National League",
            "games_played": 162,
            "runs_scored": 793,
            "runs_against": 649,
            "run_differential": 144
        },
        {
            "team_id": 113,
            "team_name": "Cincinnati Reds",
            "wins": 83,
            "losses": 79,
            "winning_percentage": ".512",
            "division_rank": "3",
            "league_rank": "6",
            "sport_rank": "13",
            "games_back": 14,
            "division_games_back": 14,
            "league_games_back": 14,
            "streak_type": "losses",
            "streak_number": 1,
            "magic_number": null,
            "elimination_number": "E",
            "division_name": "National League Central",
            "league_name": "National League",
            "games_played": 162,
            "runs_scored": 716,
            "runs_against": 681,
            "run_differential": 35
        },
        {
            "team_id": 138,
            "team_name": "St. Louis Cardinals",
            "wins": 78,
            "losses": 84,
            "winning_percentage": ".481",
            "division_rank": "4",
            "league_rank": "11",
            "sport_rank": "20",
            "games_back": 19,
            "division_games_back": 19,
            "league_games_back": 19,
            "streak_type": "losses",
            "streak_number": 4,
            "magic_number": null,
            "elimination_number": "E",
            "division_name": "National League Central",
            "league_name": "National League",
            "games_played": 162,
            "runs_scored": 689,
            "runs_against": 754,
            "run_differential": -65
        },
        {
            "team_id": 134,
            "team_name": "Pittsburgh Pirates",
            "wins": 71,
            "losses": 91,
            "winning_percentage": ".438",
            "division_rank": "5",
            "league_rank": "13",
            "sport_rank": "26",
            "games_back": 26,
            "division_games_back": 26,
            "league_games_back": 26,
            "streak_type": "losses",
            "streak_number": 1,
            "magic_number": null,
            "elimination_number": "E",
            "division_name": "National League Central",
            "league_name": "National League",
            "games_played": 162,
            "runs_scored": 583,
            "runs_against": 645,
            "run_differential": -62
        },
        {
            "team_id": 119,
            "team_name": "Los Angeles Dodgers",
            "wins": 93,
            "losses": 69,
            "winning_percentage": ".574",
            "division_rank": "1",
            "league_rank": "3",
            "sport_rank": "5",
            "games_back": "-",
            "division_games_back": "-",
            "league_games_back": 4,
            "streak_type": "wins",
            "streak_number": 5,
            "magic_number": "-",
            "elimination_number": "-",
            "division_name": "National League West",
            "league_name": "National League",
            "games_played": 162,
            "runs_scored": 825,
            "runs_against": 683,
            "run_differential": 142
        },
        {
            "team_id": 135,
            "team_name": "San Diego Padres",
            "wins": 90,
            "losses": 72,
            "winning_percentage": ".556",
            "division_rank": "2",
            "league_rank": "5",
            "sport_rank": "7",
            "games_back": 3,
            "division_games_back": 3,
            "league_games_back": 7,
            "streak_type": "wins",
            "streak_number": 3,
            "magic_number": null,
            "elimination_number": "E",
            "division_name": "National League West",
            "league_name": "National League",
            "games_played": 162,
            "runs_scored": 702,
            "runs_against": 621,
            "run_differential": 81
        },
        {
            "team_id": 137,
            "team_name": "San Francisco Giants",
            "wins": 81,
            "losses": 81,
            "winning_percentage": ".500",
            "division_rank": "3",
            "league_rank": "8",
            "sport_rank": "16",
            "games_back": 12,
            "division_games_back": 12,
            "league_games_back": 16,
            "streak_type": "wins",
            "streak_number": 4,
            "magic_number": null,
            "elimination_number": "E",
            "division_name": "National League West",
            "league_name": "National League",
            "games_played": 162,
            "runs_scored": 705,
            "runs_against": 684,
            "run_differential": 21
        },
        {
            "team_id": 109,
            "team_name": "Arizona Diamondbacks",
            "wins": 80,
            "losses": 82,
            "winning_percentage": ".494",
            "division_rank": "4",
            "league_rank": "9",
            "sport_rank": "18",
            "games_back": 13,
            "division_games_back": 13,
            "league_games_back": 17,
            "streak_type": "losses",
            "streak_number": 5,
            "magic_number": null,
            "elimination_number": "E",
            "division_name": "National League West",
            "league_name": "National League",
            "games_played": 162,
            "runs_scored": 791,
            "runs_against": 785,
            "run_differential": 6
        },
        {
            "team_id": 115,
            "team_name": "Colorado Rockies",
            "wins": 43,
            "losses": 119,
            "winning_percentage": ".265",
            "division_rank": "5",
            "league_rank": "15",
            "sport_rank": "30",
            "games_back": 50,
            "division_games_back": 50,
            "league_games_back": 54,
            "streak_type": "losses",
            "streak_number": 6,
            "magic_number": null,
            "elimination_number": "E",
            "division_name": "National League West",
            "league_name": "National League",
            "games_played": 162,
            "runs_scored": 597,
            "runs_against": 1021,
            "run_differential": -424
        }
    ]
}