[
    {
        "name":"Team Totals",
        "age":"29.5",
        "w":"42",
        "l":"28",
        "w-l%":".600",
        "era":"3.26",
        "g":"70",
        "gs":"70",
        "gf":"70",
        "cg":"0",
        "sho":"0",
        "sv":"19",
        "ip":"627.1",
        "h":"503",
        "r":"247",
        "er":"227",
        "hr":"72",
        "bb":"205",
        "ibb":"6",
        "so":"605",
        "hbp":"24",
        "bk":"2",
        "wp":"25",
        "bf":"2559",
        "era+":"124",
        "fip":"3.81",
        "whip":"1.129",
        "h9":"7.2",
        "hr9":"1.0",
        "bb9":"2.9",
        "so9":"8.7",
        "so\/w":"2.95",
        "season":"2024"
    }
]