[
    {
        "name":"Team Totals",
        "war":"1.2",
        "w":"9",
        "l":"2",
        "w-l%":".818",
        "era":"2.48",
        "g":"11",
        "gs":"11",
        "gf":"11",
        "cg":"0",
        "sho":"0",
        "sv":"5",
        "ip":"98.0",
        "h":"66",
        "r":"35",
        "er":"27",
        "hr":"5",
        "bb":"54",
        "ibb":"2",
        "so":"113",
        "hbp":"2",
        "bk":"0",
        "wp":"8",
        "bf":"408",
        "era+":"163",
        "fip":"3.16",
        "whip":"1.224",
        "h9":"6.1",
        "hr9":"0.5",
        "bb9":"5.0",
        "so9":"10.4",
        "so\/bb":"2.09",
        "season":"2025"
    }
]