[
    {
        "name":"Team Totals",
        "age":"29.5",
        "w":"51",
        "l":"31",
        "w-l%":".622",
        "era":"3.25",
        "g":"82",
        "gs":"82",
        "gf":"81",
        "cg":"1",
        "sho":"1",
        "sv":"25",
        "ip":"736.0",
        "h":"575",
        "r":"289",
        "er":"266",
        "hr":"83",
        "bb":"237",
        "ibb":"7",
        "so":"703",
        "hbp":"30",
        "bk":"2",
        "wp":"28",
        "bf":"2989",
        "era+":"123",
        "fip":"3.80",
        "whip":"1.103",
        "h9":"7.0",
        "hr9":"1.0",
        "bb9":"2.9",
        "so9":"8.6",
        "so\/w":"2.97",
        "season":"2024"
    }
]