[
    {
        "name":"Team Totals",
        "war":"1.2",
        "w":"8",
        "l":"1",
        "w-l%":".889",
        "era":"2.00",
        "g":"9",
        "gs":"9",
        "gf":"9",
        "cg":"0",
        "sho":"0",
        "sv":"4",
        "ip":"81.0",
        "h":"56",
        "r":"26",
        "er":"18",
        "hr":"4",
        "bb":"41",
        "ibb":"2",
        "so":"98",
        "hbp":"1",
        "bk":"0",
        "wp":"5",
        "bf":"336",
        "era+":"193",
        "fip":"2.70",
        "whip":"1.198",
        "h9":"6.2",
        "hr9":"0.4",
        "bb9":"4.6",
        "so9":"10.9",
        "so\/bb":"2.39",
        "season":"2025"
    }
]